dufomap_bind.cpython-38-x86_64-linux-gnu.so
dufomap/__init__.py
dufomap/utils/__init__.py
dufomap/utils/pose.py
dufomap/utils/pcdpy3.py
dufomap/utils/o3d_view.py
dufomap-1.1.0.dist-info/RECORD
dufomap-1.1.0.dist-info/METADATA
dufomap-1.1.0.dist-info/WHEEL
