Metadata-Version: 2.1
Name: dufomap
Version: 1.1.0
Summary: DUFOMap Python bindings
Author-Email: Qingwen Zhang <qzhangcb@connect.ust.hk>
Classifier: License :: OSI Approved :: BSD License
Classifier: Operating System :: MacOS
Classifier: Operating System :: Microsoft :: Windows
Classifier: Operating System :: Unix
Classifier: Programming Language :: C++
Classifier: Programming Language :: Python :: 3
Classifier: Programming Language :: Python :: 3.8
Classifier: Programming Language :: Python :: 3.9
Classifier: Programming Language :: Python :: 3.10
Project-URL: Github, https://github.com/Kin-Zhang/dufomap
Project-URL: Webpage, https://kin-zhang.github.io//dufomap
Requires-Python: >=3.8
Requires-Dist: numpy
